{
	"easycom": {
		"^u-(.*)": "@/uview-ui/components/u-$1/u-$1.vue"
	},

	"pages": [ //pages数组中第一项表示应用启动页，参考：https://uniapp.dcloud.io/collocation/pages
		
		{
			"path": "pages/index/index",
			"style": {
				"navigationBarTitleText": "智慧农场",
				"navigationStyle": "custom", // 隐藏系统导航栏
				"navigationBarTextStyle": "white" // 状态栏字体为白色，只能为 white-白色，black-黑色 二选一
			}
		},
		{
			"path": "pages/manage/manage",
			"style": {
				"navigationBarTitleText": "地块管理",
				"navigationStyle": "custom", // 隐藏系统导航栏
				"navigationBarTextStyle": "white" // 状态栏字体为白色，只能为 white-白色，black-黑色 二选一
			}

		},
		{
			"path": "pages/farm/farm",
			"style": {
				"navigationBarTitleText": "我的",
				"navigationStyle": "custom", // 隐藏系统导航栏
				"navigationBarTextStyle": "white" // 状态栏字体为白色，只能为 white-白色，black-黑色 二选一
			}

		},
		{
			"path": "pages/DataAnalysis/DataAnalysis",
			"style": {
				"navigationBarTitleText": "数据分析",
				"navigationStyle": "custom", // 隐藏系统导航栏
				"navigationBarTextStyle": "white" // 状态栏字体为白色，只能为 white-白色，black-黑色 二选一
			}

		},
		{
			"path": "pages/selectArea/selectArea",
			"style": {
				"navigationBarTitleText": "地区选择",
				"navigationStyle": "custom", // 隐藏系统导航栏
				"navigationBarTextStyle": "white" // 状态栏字体为白色，只能为 white-白色，black-黑色 二选一
			}

		},

		{
			"path": "pages/modAlert/modAlert",
			"style": {
				"navigationBarTitleText": "设置预警值",
				"navigationStyle": "custom", // 隐藏系统导航栏
				"navigationBarTextStyle": "white" // 状态栏字体为白色，只能为 white-白色，black-黑色 二选一
			}

		}


        ,{
            "path" : "pages/monitor/monitor",
            "style" :                                                                                    
            {
               "navigationBarTitleText": "实时监控",
               "navigationStyle": "custom", // 隐藏系统导航栏
               "navigationBarTextStyle": "white" // 状态栏字体为白色，只能为 white-白色，black-黑色 二选一
            }
            
        }
    ],
	"globalStyle": {
		"navigationBarTextStyle": "black",
		"navigationBarTitleText": "uni-app",
		"navigationBarBackgroundColor": "#F8F8F8",
		"backgroundColor": "#F8F8F8"
	}
}
